pysqsd/__init__.py
pysqsd/__main__.py
pysqsd-0.0.1.dist-info/DESCRIPTION.rst
pysqsd-0.0.1.dist-info/entry_points.txt
pysqsd-0.0.1.dist-info/METADATA
pysqsd-0.0.1.dist-info/metadata.json
pysqsd-0.0.1.dist-info/RECORD
pysqsd-0.0.1.dist-info/top_level.txt
pysqsd-0.0.1.dist-info/WHEEL
