Metadata-Version: 2.0
Name: pysqsd
Version: 0.0.1
Summary: SQS Daemon inspired by Elastic Beanstalk's sqsd
Home-page: http://github.com/flovilmart/pysqsd/tree/master
Author: Florent Vilmart
Author-email: florentvilmart@me.com
License: MIT
Keywords: aws sqs queue
Platform: UNKNOWN
Classifier: Development Status :: 4 - Beta
Classifier: Intended Audience :: Developers
Classifier: License :: OSI Approved :: MIT License
Classifier: Operating System :: OS Independent
Classifier: Programming Language :: Python
Requires-Dist: boto
